<?xml version="1.0" encoding="utf-8"?>
<openerp>
<data>


        <record model="ir.ui.view" id="view_account_invoice_supplier_search">
            <field name="name">view.account.invoice.supplier.search</field>
            <field name="model">account.invoice</field>
            <field name="inherit_id" ref="account.view_account_invoice_filter" />
            <field name="arch" type="xml">
                <xpath expr="/search" position="inside">
                    <field name="reference" string="Ref/Nº Factura"/>
                </xpath>
            </field>
        </record>


</data>
</openerp>
